pyga/__init__.py
pyga/entities.py
pyga/exceptions.py
pyga/requests.py
pyga/utils.py
tests/__init__.py
tests/ga.py
tests/serialize.py
tests/utils.py
pyga-2.6.2.dist-info/LICENSE
pyga-2.6.2.dist-info/METADATA
pyga-2.6.2.dist-info/WHEEL
pyga-2.6.2.dist-info/top_level.txt
pyga-2.6.2.dist-info/RECORD
