Metadata-Version: 1.1
Name: pyga
Version: 2.6.2
Summary: Server side implementation of Google Analytics in Python.
Home-page: http://kra3.github.com/py-ga-mob/
Author: Arun K.R.
Author-email: the1.arun@gmail.com
License: Simplified BSD
Keywords: Google analytics  mobile server side
Platform: UNKNOWN
Classifier: Intended Audience :: Developers
Classifier: License :: OSI Approved :: BSD License
Classifier: Environment :: Web Environment
Classifier: Development Status :: 5 - Production/Stable
Classifier: Programming Language :: Python
Classifier: Operating System :: OS Independent
Classifier: Topic :: Software Development :: Libraries :: Python Modules
Classifier: Topic :: Internet
Classifier: Topic :: Internet :: WWW/HTTP
Classifier: Topic :: Internet :: WWW/HTTP :: WSGI
Requires: six
